LICENSE
localnow/__init__.py
localnow/localnow.py
localnow-0.1.0.dist-info/LICENSE
localnow-0.1.0.dist-info/WHEEL
localnow-0.1.0.dist-info/METADATA
localnow-0.1.0.dist-info/RECORD
